Metadata-Version: 1.0
Name: enum
Version: 0.4.2
Summary: Robust enumerated type support in Python
Home-page: http://cheeseshop.python.org/pypi/enum/
Author: Ben Finney
Author-email: ben+python@benfinney.id.au
License: Choice of GPL or Python license
Keywords: enum enumerated enumeration
Platform: UNKNOWN
Classifier: Development Status :: 4 - Beta
Classifier: License :: OSI Approved :: GNU General Public License (GPL)
Classifier: License :: OSI Approved :: Python Software Foundation License
Classifier: Programming Language :: Python
Classifier: Topic :: Software Development :: Libraries :: Python Modules
Classifier: Operating System :: OS Independent
Classifier: Intended Audience :: Developers
